{
  "id": 299,
  "first_name": "Mariano",
  "last_name": "Pepitez",
  "items": [
    {
      "id": 11440,
      "title": "Arkham Horror (Third Edition) (2018)",
      "delivered": true,
      "elements": [
        {
          "id": 13531,
          "primary_name": "Arkham Horror (Third Edition)"
        }
      ]
    },
    {
      "id": 11158,
      "title": "5-Minute Dungeon (2017) + 5-Minute Dungeon: Curses! Foiled Again! (2018)",
      "delivered": false,
      "elements": [
        {
          "id": 13209,
          "primary_name": "5-Minute Dungeon: Curses! Foiled Again!"
        },
        {
          "id": 13208,
          "primary_name": "5-Minute Dungeon"
        }
      ]
    },
    {
      "id": 18030,
      "title": "A Feast for Odin (2016) + A Feast for Odin: The Norwegians (2018)",
      "delivered": false,
      "elements": [
        {
          "id": 21285,
          "primary_name": "A Feast for Odin"
        },
        {
          "id": 21286,
          "primary_name": "A Feast for Odin: The Norwegians"
        }
      ]
    }
  ]
}